{
    "2023-02-07": {
        "price": {
            "open": 105,
            "max": 105,
            "min": 105,
            "close": 105,
            "prevClose": 105,
            "diff": 0
        },
        "numTrans": 1,
        "tradedShares": 300000,
        "amount": 31500000,
        "indicators": {
            "SMA": null,
            "EMA": null,
            "RSI": null,
            "MACD": null,
            "MACD_Signal": null,
            "MACD_Hist": null,
            "BB_High": null,
            "BB_Low": null,
            "BB_Mid": null
        }
    },
    "2023-02-08": {
        "price": {
            "open": 105,
            "max": 105,
            "min": 105,
            "close": 105,
            "prevClose": 105,
            "diff": 0
        },
        "numTrans": 1,
        "tradedShares": 309310,
        "amount": 32477550,
        "indicators": {
            "SMA": null,
            "EMA": null,
            "RSI": null,
            "MACD": null,
            "MACD_Signal": null,
            "MACD_Hist": null,
            "BB_High": null,
            "BB_Low": null,
            "BB_Mid": null
        }
    },
    "2023-04-11": {
        "price": {
            "open": 100,
            "max": 100,
            "min": 100,
            "close": 100,
            "prevClose": 100,
            "diff": 0
        },
        "numTrans": 1,
        "tradedShares": 30650,
        "amount": 3065000,
        "indicators": {
            "SMA": null,
            "EMA": null,
            "RSI": null,
            "MACD": null,
            "MACD_Signal": null,
            "MACD_Hist": null,
            "BB_High": null,
            "BB_Low": null,
            "BB_Mid": null
        }
    },
    "2023-04-18": {
        "price": {
            "open": 102,
            "max": 102,
            "min": 102,
            "close": 102,
            "prevClose": 100,
            "diff": 2
        },
        "numTrans": 2,
        "tradedShares": 516001,
        "amount": 52632102,
        "indicators": {
            "SMA": null,
            "EMA": null,
            "RSI": null,
            "MACD": null,
            "MACD_Signal": null,
            "MACD_Hist": null,
            "BB_High": null,
            "BB_Low": null,
            "BB_Mid": null
        }
    },
    "2023-05-14": {
        "price": {
            "open": 102,
            "max": 102,
            "min": 102,
            "close": 102,
            "prevClose": 102,
            "diff": 0
        },
        "numTrans": 2,
        "tradedShares": 119518,
        "amount": 12190836,
        "indicators": {
            "SMA": null,
            "EMA": null,
            "RSI": null,
            "MACD": null,
            "MACD_Signal": null,
            "MACD_Hist": null,
            "BB_High": null,
            "BB_Low": null,
            "BB_Mid": null
        }
    },
    "2023-05-31": {
        "price": {
            "open": 102,
            "max": 102,
            "min": 102,
            "close": 102,
            "prevClose": 102,
            "diff": 0
        },
        "numTrans": 4,
        "tradedShares": 2787123,
        "amount": 342816129,
        "indicators": {
            "SMA": null,
            "EMA": null,
            "RSI": null,
            "MACD": null,
            "MACD_Signal": null,
            "MACD_Hist": null,
            "BB_High": null,
            "BB_Low": null,
            "BB_Mid": null
        }
    },
    "2023-06-01": {
        "price": {
            "open": 102,
            "max": 102,
            "min": 102,
            "close": 102,
            "prevClose": 102,
            "diff": 0
        },
        "numTrans": 3,
        "tradedShares": 1887273,
        "amount": 232134579,
        "indicators": {
            "SMA": null,
            "EMA": null,
            "RSI": null,
            "MACD": null,
            "MACD_Signal": null,
            "MACD_Hist": null,
            "BB_High": null,
            "BB_Low": null,
            "BB_Mid": null
        }
    },
    "2023-06-19": {
        "price": {
            "open": 102,
            "max": 102,
            "min": 100,
            "close": 100,
            "prevClose": 102,
            "diff": -2
        },
        "numTrans": 2,
        "tradedShares": 103018,
        "amount": 10367836,
        "indicators": {
            "SMA": null,
            "EMA": null,
            "RSI": null,
            "MACD": null,
            "MACD_Signal": null,
            "MACD_Hist": null,
            "BB_High": null,
            "BB_Low": null,
            "BB_Mid": null
        }
    },
    "2023-06-20": {
        "price": {
            "open": 102,
            "max": 102,
            "min": 102,
            "close": 102,
            "prevClose": 100,
            "diff": 2
        },
        "numTrans": 1,
        "tradedShares": 13305,
        "amount": 1357110,
        "indicators": {
            "SMA": null,
            "EMA": null,
            "RSI": null,
            "MACD": null,
            "MACD_Signal": null,
            "MACD_Hist": null,
            "BB_High": null,
            "BB_Low": null,
            "BB_Mid": null
        }
    },
    "2023-06-21": {
        "price": {
            "open": 100,
            "max": 100,
            "min": 100,
            "close": 100,
            "prevClose": 102,
            "diff": -2
        },
        "numTrans": 1,
        "tradedShares": 64218,
        "amount": 6421800,
        "indicators": {
            "SMA": null,
            "EMA": null,
            "RSI": null,
            "MACD": null,
            "MACD_Signal": null,
            "MACD_Hist": null,
            "BB_High": null,
            "BB_Low": null,
            "BB_Mid": null
        }
    },
    "2023-06-22": {
        "price": {
            "open": 100,
            "max": 100,
            "min": 100,
            "close": 100,
            "prevClose": 100,
            "diff": 0
        },
        "numTrans": 1,
        "tradedShares": 29000,
        "amount": 2900000,
        "indicators": {
            "SMA": null,
            "EMA": null,
            "RSI": null,
            "MACD": null,
            "MACD_Signal": null,
            "MACD_Hist": null,
            "BB_High": null,
            "BB_Low": null,
            "BB_Mid": null
        }
    },
    "2023-06-25": {
        "price": {
            "open": 100,
            "max": 100,
            "min": 100,
            "close": 100,
            "prevClose": 100,
            "diff": 0
        },
        "numTrans": 1,
        "tradedShares": 86468,
        "amount": 8646800,
        "indicators": {
            "SMA": null,
            "EMA": null,
            "RSI": null,
            "MACD": null,
            "MACD_Signal": null,
            "MACD_Hist": null,
            "BB_High": null,
            "BB_Low": null,
            "BB_Mid": null
        }
    },
    "2023-07-06": {
        "price": {
            "open": 100,
            "max": 100,
            "min": 100,
            "close": 100,
            "prevClose": 100,
            "diff": 0
        },
        "numTrans": 5,
        "tradedShares": 1697526,
        "amount": 169752600,
        "indicators": {
            "SMA": null,
            "EMA": null,
            "RSI": null,
            "MACD": null,
            "MACD_Signal": null,
            "MACD_Hist": null,
            "BB_High": null,
            "BB_Low": null,
            "BB_Mid": null
        }
    },
    "2023-07-10": {
        "price": {
            "open": 100,
            "max": 100,
            "min": 100,
            "close": 100,
            "prevClose": 100,
            "diff": 0
        },
        "numTrans": 2,
        "tradedShares": 6791,
        "amount": 679100,
        "indicators": {
            "SMA": null,
            "EMA": null,
            "RSI": 31.902757127724755,
            "MACD": null,
            "MACD_Signal": null,
            "MACD_Hist": null,
            "BB_High": null,
            "BB_Low": null,
            "BB_Mid": null
        }
    },
    "2023-07-11": {
        "price": {
            "open": 100,
            "max": 100,
            "min": 100,
            "close": 100,
            "prevClose": 100,
            "diff": 0
        },
        "numTrans": 1,
        "tradedShares": 18960,
        "amount": 1896000,
        "indicators": {
            "SMA": null,
            "EMA": null,
            "RSI": 31.902757127724755,
            "MACD": null,
            "MACD_Signal": null,
            "MACD_Hist": null,
            "BB_High": null,
            "BB_Low": null,
            "BB_Mid": null
        }
    },
    "2023-07-12": {
        "price": {
            "open": 102,
            "max": 110,
            "min": 102,
            "close": 110,
            "prevClose": 100,
            "diff": 10
        },
        "numTrans": 5,
        "tradedShares": 200040,
        "amount": 20404280,
        "indicators": {
            "SMA": null,
            "EMA": null,
            "RSI": 73.65982744053122,
            "MACD": null,
            "MACD_Signal": null,
            "MACD_Hist": null,
            "BB_High": null,
            "BB_Low": null,
            "BB_Mid": null
        }
    },
    "2023-07-13": {
        "price": {
            "open": 112,
            "max": 115,
            "min": 112,
            "close": 115,
            "prevClose": 110,
            "diff": 5
        },
        "numTrans": 3,
        "tradedShares": 156490,
        "amount": 17996310,
        "indicators": {
            "SMA": null,
            "EMA": null,
            "RSI": 80.19808893187262,
            "MACD": null,
            "MACD_Signal": null,
            "MACD_Hist": null,
            "BB_High": null,
            "BB_Low": null,
            "BB_Mid": null
        }
    },
    "2023-07-16": {
        "price": {
            "open": 115,
            "max": 115,
            "min": 113,
            "close": 113,
            "prevClose": 115,
            "diff": -2
        },
        "numTrans": 3,
        "tradedShares": 137900,
        "amount": 15599822,
        "indicators": {
            "SMA": null,
            "EMA": null,
            "RSI": 72.45109367001828,
            "MACD": null,
            "MACD_Signal": null,
            "MACD_Hist": null,
            "BB_High": null,
            "BB_Low": null,
            "BB_Mid": null
        }
    },
    "2023-07-19": {
        "price": {
            "open": 115,
            "max": 115,
            "min": 115,
            "close": 115,
            "prevClose": 113,
            "diff": 2
        },
        "numTrans": 1,
        "tradedShares": 47168,
        "amount": 5424320,
        "indicators": {
            "SMA": null,
            "EMA": null,
            "RSI": 75.04693342635163,
            "MACD": null,
            "MACD_Signal": null,
            "MACD_Hist": null,
            "BB_High": null,
            "BB_Low": null,
            "BB_Mid": null
        }
    },
    "2023-07-20": {
        "price": {
            "open": 115,
            "max": 115,
            "min": 115,
            "close": 115,
            "prevClose": 115,
            "diff": 0
        },
        "numTrans": 1,
        "tradedShares": 200000,
        "amount": 23000000,
        "indicators": {
            "SMA": 104.4,
            "EMA": 106.49904276191428,
            "RSI": 75.04693342635163,
            "MACD": null,
            "MACD_Signal": null,
            "MACD_Hist": null,
            "BB_High": 115.59642800182273,
            "BB_Low": 93.20357199817728,
            "BB_Mid": 104.4
        }
    },
    "2023-08-13": {
        "price": {
            "open": 115,
            "max": 115,
            "min": 115,
            "close": 115,
            "prevClose": 115,
            "diff": 0
        },
        "numTrans": 1,
        "tradedShares": 33921,
        "amount": 3900915,
        "indicators": {
            "SMA": 104.9,
            "EMA": 107.30865773697006,
            "RSI": 75.04693342635163,
            "MACD": null,
            "MACD_Signal": null,
            "MACD_Hist": null,
            "BB_High": 117.01445417672626,
            "BB_Low": 92.78554582327375,
            "BB_Mid": 104.9
        }
    },
    "2023-08-27": {
        "price": {
            "open": 113,
            "max": 113,
            "min": 111,
            "close": 111,
            "prevClose": 115,
            "diff": -4
        },
        "numTrans": 2,
        "tradedShares": 22000,
        "amount": 2462000,
        "indicators": {
            "SMA": 105.2,
            "EMA": 107.66021414297292,
            "RSI": 60.74837569796044,
            "MACD": null,
            "MACD_Signal": null,
            "MACD_Hist": null,
            "BB_High": 117.60322538697093,
            "BB_Low": 92.79677461302907,
            "BB_Mid": 105.2
        }
    },
    "2023-08-28": {
        "price": {
            "open": 111,
            "max": 111,
            "min": 111,
            "close": 111,
            "prevClose": 111,
            "diff": 0
        },
        "numTrans": 1,
        "tradedShares": 54695,
        "amount": 6071145,
        "indicators": {
            "SMA": 105.75,
            "EMA": 107.97828898649931,
            "RSI": 60.74837569796044,
            "MACD": null,
            "MACD_Signal": null,
            "MACD_Hist": null,
            "BB_High": 118.15765892503498,
            "BB_Low": 93.34234107496502,
            "BB_Mid": 105.75
        }
    },
    "2023-09-12": {
        "price": {
            "open": 111,
            "max": 111,
            "min": 111,
            "close": 111,
            "prevClose": 111,
            "diff": 0
        },
        "numTrans": 1,
        "tradedShares": 89456,
        "amount": 9392880,
        "indicators": {
            "SMA": 106.2,
            "EMA": 108.26607098778508,
            "RSI": 60.74837569796044,
            "MACD": null,
            "MACD_Signal": null,
            "MACD_Hist": null,
            "BB_High": 118.6835892274618,
            "BB_Low": 93.71641077253821,
            "BB_Mid": 106.2
        }
    },
    "2023-09-13": {
        "price": {
            "open": 109,
            "max": 109,
            "min": 109,
            "close": 109,
            "prevClose": 111,
            "diff": -2
        },
        "numTrans": 1,
        "tradedShares": 14474,
        "amount": 1577666,
        "indicators": {
            "SMA": 106.55,
            "EMA": 108.33596898894841,
            "RSI": 54.28893841068774,
            "MACD": null,
            "MACD_Signal": null,
            "MACD_Hist": null,
            "BB_High": 118.93507165905794,
            "BB_Low": 94.16492834094205,
            "BB_Mid": 106.55
        }
    },
    "2023-09-19": {
        "price": {
            "open": 109,
            "max": 109,
            "min": 109,
            "close": 109,
            "prevClose": 109,
            "diff": 0
        },
        "numTrans": 1,
        "tradedShares": 68366,
        "amount": 7451894,
        "indicators": {
            "SMA": 106.9,
            "EMA": 108.39921003762,
            "RSI": 54.28893841068774,
            "MACD": 1.999383829392798,
            "MACD_Signal": null,
            "MACD_Hist": null,
            "BB_High": 119.14581561187332,
            "BB_Low": 94.6541843881267,
            "BB_Mid": 106.9
        }
    },
    "2023-10-03": {
        "price": {
            "open": 109,
            "max": 109,
            "min": 109,
            "close": 109,
            "prevClose": 109,
            "diff": 0
        },
        "numTrans": 1,
        "tradedShares": 128381,
        "amount": 14763815,
        "indicators": {
            "SMA": 107.25,
            "EMA": 108.45642812927524,
            "RSI": 54.28893841068774,
            "MACD": 1.7952104475992314,
            "MACD_Signal": null,
            "MACD_Hist": null,
            "BB_High": 119.31441047047058,
            "BB_Low": 95.18558952952942,
            "BB_Mid": 107.25
        }
    },
    "2023-10-12": {
        "price": {
            "open": 109,
            "max": 109,
            "min": 109,
            "close": 109,
            "prevClose": 109,
            "diff": 0
        },
        "numTrans": 3,
        "tradedShares": 9555,
        "amount": 1041495,
        "indicators": {
            "SMA": 107.7,
            "EMA": 108.50819687886808,
            "RSI": 54.28893841068774,
            "MACD": 1.614787308614524,
            "MACD_Signal": null,
            "MACD_Hist": null,
            "BB_High": 119.31206269359583,
            "BB_Low": 96.08793730640417,
            "BB_Mid": 107.7
        }
    },
    "2023-10-16": {
        "price": {
            "open": 109,
            "max": 109,
            "min": 108,
            "close": 108,
            "prevClose": 109,
            "diff": -1
        },
        "numTrans": 3,
        "tradedShares": 578094,
        "amount": 62476893,
        "indicators": {
            "SMA": 108.0,
            "EMA": 108.45979717611874,
            "RSI": 50.665809864395946,
            "MACD": 1.375255934098135,
            "MACD_Signal": null,
            "MACD_Hist": null,
            "BB_High": 119.31370849898477,
            "BB_Low": 96.68629150101523,
            "BB_Mid": 108.0
        }
    },
    "2023-10-17": {
        "price": {
            "open": 108,
            "max": 108,
            "min": 108,
            "close": 108,
            "prevClose": 108,
            "diff": 0
        },
        "numTrans": 1,
        "tradedShares": 32000,
        "amount": 3456000,
        "indicators": {
            "SMA": 108.4,
            "EMA": 108.41600696886934,
            "RSI": 50.665809864395946,
            "MACD": 1.1719164704844616,
            "MACD_Signal": null,
            "MACD_Hist": null,
            "BB_High": 119.10327052820774,
            "BB_Low": 97.69672947179227,
            "BB_Mid": 108.4
        }
    },
    "2023-10-19": {
        "price": {
            "open": 108,
            "max": 108,
            "min": 108,
            "close": 108,
            "prevClose": 108,
            "diff": 0
        },
        "numTrans": 1,
        "tradedShares": 477200,
        "amount": 51537600,
        "indicators": {
            "SMA": 108.8,
            "EMA": 108.37638725754846,
            "RSI": 50.665809864395946,
            "MACD": 0.9992497514653849,
            "MACD_Signal": null,
            "MACD_Hist": null,
            "BB_High": 118.79199679743745,
            "BB_Low": 98.80800320256255,
            "BB_Mid": 108.8
        }
    },
    "2023-11-01": {
        "price": {
            "open": 108,
            "max": 108,
            "min": 108,
            "close": 108,
            "prevClose": 108,
            "diff": 0
        },
        "numTrans": 1,
        "tradedShares": 28374,
        "amount": 2837400,
        "indicators": {
            "SMA": 109.2,
            "EMA": 108.34054085206765,
            "RSI": 50.665809864395946,
            "MACD": 0.8525820969465485,
            "MACD_Signal": null,
            "MACD_Hist": null,
            "BB_High": 118.3564185138077,
            "BB_Low": 100.04358148619231,
            "BB_Mid": 109.2
        }
    },
    "2023-11-23": {
        "price": {
            "open": 105.9,
            "max": 105.9,
            "min": 105.9,
            "close": 105.9,
            "prevClose": 108,
            "diff": -2.0999999999999943
        },
        "numTrans": 1,
        "tradedShares": 15069,
        "amount": 1595807.1,
        "indicators": {
            "SMA": 109.495,
            "EMA": 108.10810838996598,
            "RSI": 42.62974931394355,
            "MACD": 0.5604341385976426,
            "MACD_Signal": null,
            "MACD_Hist": null,
            "BB_High": 117.78607351312245,
            "BB_Low": 101.20392648687756,
            "BB_Mid": 109.495
        }
    },
    "2023-11-26": {
        "price": {
            "open": 105.9,
            "max": 105.9,
            "min": 105.9,
            "close": 105.9,
            "prevClose": 105.9,
            "diff": 0
        },
        "numTrans": 1,
        "tradedShares": 21370,
        "amount": 2263083,
        "indicators": {
            "SMA": 109.79,
            "EMA": 107.89781235282636,
            "RSI": 42.62974931394355,
            "MACD": 0.32515657420920263,
            "MACD_Signal": 1.0476855183200828,
            "MACD_Hist": -0.7225289441108802,
            "BB_High": 117.06651015253883,
            "BB_Low": 102.51348984746119,
            "BB_Mid": 109.79
        }
    },
    "2023-11-27": {
        "price": {
            "open": 105.9,
            "max": 105.9,
            "min": 105.9,
            "close": 105.9,
            "prevClose": 105.9,
            "diff": 0
        },
        "numTrans": 1,
        "tradedShares": 497369,
        "amount": 52671377.1,
        "indicators": {
            "SMA": 110.085,
            "EMA": 107.70754450970004,
            "RSI": 42.62974931394355,
            "MACD": 0.1371168120905395,
            "MACD_Signal": 0.8655717770741742,
            "MACD_Hist": -0.7284549649836347,
            "BB_High": 116.12297151367912,
            "BB_Low": 104.04702848632087,
            "BB_Mid": 110.085
        }
    },
    "2023-11-28": {
        "price": {
            "open": 105.9,
            "max": 105.9,
            "min": 105.9,
            "close": 105.9,
            "prevClose": 105.9,
            "diff": 0
        },
        "numTrans": 1,
        "tradedShares": 10935,
        "amount": 1158016.5,
        "indicators": {
            "SMA": 109.88,
            "EMA": 107.53539741353813,
            "RSI": 42.62974931394355,
            "MACD": -0.01177037261317082,
            "MACD_Signal": 0.6901033471367053,
            "MACD_Hist": -0.7018737197498761,
            "BB_High": 116.1879632211991,
            "BB_Low": 103.57203677880089,
            "BB_Mid": 109.88
        }
    },
    "2023-11-29": {
        "price": {
            "open": 105.9,
            "max": 105.9,
            "min": 105.9,
            "close": 104,
            "prevClose": 105.9,
            "diff": -1.9000000000000057
        },
        "numTrans": 1,
        "tradedShares": 736984,
        "amount": 76646336,
        "indicators": {
            "SMA": 109.33,
            "EMA": 107.19869289796307,
            "RSI": 35.732650039672095,
            "MACD": -0.27985269256492984,
            "MACD_Signal": 0.4961121391963783,
            "MACD_Hist": -0.7759648317613081,
            "BB_High": 115.67447791390279,
            "BB_Low": 102.9855220860972,
            "BB_Mid": 109.33
        }
    },
    "2023-11-30": {
        "price": {
            "open": 104,
            "max": 104,
            "min": 104,
            "close": 104,
            "prevClose": 104,
            "diff": 0
        },
        "numTrans": 1,
        "tradedShares": 27000,
        "amount": 2808000,
        "indicators": {
            "SMA": 108.88,
            "EMA": 106.89405547910945,
            "RSI": 35.732650039672095,
            "MACD": -0.48669949375145904,
            "MACD_Signal": 0.29954981260681085,
            "MACD_Hist": -0.7862493063582698,
            "BB_High": 115.3938621416177,
            "BB_Low": 102.36613785838229,
            "BB_Mid": 108.88
        }
    },
    "2023-12-03": {
        "price": {
            "open": 104,
            "max": 104,
            "min": 104,
            "close": 104,
            "prevClose": 104,
            "diff": 0
        },
        "numTrans": 1,
        "tradedShares": 39409,
        "amount": 4098536,
        "indicators": {
            "SMA": 108.33,
            "EMA": 106.6184311477657,
            "RSI": 35.732650039672095,
            "MACD": -0.6432125203933055,
            "MACD_Signal": 0.1109973460067876,
            "MACD_Hist": -0.754209866400093,
            "BB_High": 114.53422436731621,
            "BB_Low": 102.12577563268378,
            "BB_Mid": 108.33
        }
    },
    "2023-12-11": {
        "price": {
            "open": 104,
            "max": 104,
            "min": 104,
            "close": 104,
            "prevClose": 104,
            "diff": 0
        },
        "numTrans": 1,
        "tradedShares": 4267,
        "amount": 443768,
        "indicators": {
            "SMA": 107.78,
            "EMA": 106.36905675274039,
            "RSI": 35.732650039672095,
            "MACD": -0.758506629353235,
            "MACD_Signal": -0.06290344906521692,
            "MACD_Hist": -0.695603180288018,
            "BB_High": 113.44872119617821,
            "BB_Low": 102.11127880382179,
            "BB_Mid": 107.78
        }
    },
    "2023-12-19": {
        "price": {
            "open": 104,
            "max": 104,
            "min": 102,
            "close": 102,
            "prevClose": 104,
            "diff": -2
        },
        "numTrans": 4,
        "tradedShares": 906413,
        "amount": 92464126,
        "indicators": {
            "SMA": 107.13,
            "EMA": 105.95295610962225,
            "RSI": 29.072909333621396,
            "MACD": -0.9997369810528625,
            "MACD_Signal": -0.25027015546274606,
            "MACD_Hist": -0.7494668255901165,
            "BB_High": 112.29724297861056,
            "BB_Low": 101.96275702138944,
            "BB_Mid": 107.13
        }
    },
    "2024-03-21": {
        "price": {
            "open": 102,
            "max": 102,
            "min": 102,
            "close": 102,
            "prevClose": 102,
            "diff": 0
        },
        "numTrans": 1,
        "tradedShares": 294875,
        "amount": 30077250,
        "indicators": {
            "SMA": 106.67999999999999,
            "EMA": 105.57648409918203,
            "RSI": 29.072909333621396,
            "MACD": -1.1773421058197755,
            "MACD_Signal": -0.435684545534152,
            "MACD_Hist": -0.7416575602856235,
            "BB_High": 111.98644890675487,
            "BB_Low": 101.37355109324511,
            "BB_Mid": 106.67999999999999
        }
    },
    "2024-03-31": {
        "price": {
            "open": 102,
            "max": 102,
            "min": 102,
            "close": 102,
            "prevClose": 102,
            "diff": 0
        },
        "numTrans": 2,
        "tradedShares": 25830,
        "amount": 2634660,
        "indicators": {
            "SMA": 106.22999999999999,
            "EMA": 105.23586656592659,
            "RSI": 29.072909333621396,
            "MACD": -1.3030744160409142,
            "MACD_Signal": -0.6091625196355045,
            "MACD_Hist": -0.6939118964054097,
            "BB_High": 111.52116244316879,
            "BB_Low": 100.93883755683119,
            "BB_Mid": 106.22999999999999
        }
    },
    "2024-04-03": {
        "price": {
            "open": 102,
            "max": 102,
            "min": 102,
            "close": 102,
            "prevClose": 102,
            "diff": 0
        },
        "numTrans": 1,
        "tradedShares": 241674,
        "amount": 24650748,
        "indicators": {
            "SMA": 105.78,
            "EMA": 104.9276887977431,
            "RSI": 29.072909333621396,
            "MACD": -1.3867327854045897,
            "MACD_Signal": -0.7646765727893216,
            "MACD_Hist": -0.6220562126152681,
            "BB_High": 110.9,
            "BB_Low": 100.66,
            "BB_Mid": 105.78
        }
    },
    "2024-04-16": {
        "price": {
            "open": 102,
            "max": 102,
            "min": 102,
            "close": 102,
            "prevClose": 102,
            "diff": 0
        },
        "numTrans": 1,
        "tradedShares": 1000,
        "amount": 102000,
        "indicators": {
            "SMA": 105.42999999999999,
            "EMA": 104.64886129319613,
            "RSI": 29.072909333621396,
            "MACD": -1.4364738692604107,
            "MACD_Signal": -0.8990360320835394,
            "MACD_Hist": -0.5374378371768712,
            "BB_High": 110.57863088597347,
            "BB_Low": 100.28136911402652,
            "BB_Mid": 105.42999999999999
        }
    },
    "2024-04-18": {
        "price": {
            "open": 102,
            "max": 102,
            "min": 102,
            "close": 102,
            "prevClose": 102,
            "diff": 0
        },
        "numTrans": 1,
        "tradedShares": 1000,
        "amount": 102000,
        "indicators": {
            "SMA": 105.08,
            "EMA": 104.39658878908222,
            "RSI": 29.072909333621396,
            "MACD": -1.4590747313211239,
            "MACD_Signal": -1.0110437719310563,
            "MACD_Hist": -0.44803095939006754,
            "BB_High": 110.16157455913027,
            "BB_Low": 99.99842544086972,
            "BB_Mid": 105.08
        }
    },
    "2024-04-22": {
        "price": {
            "open": 102,
            "max": 102,
            "min": 102,
            "close": 102,
            "prevClose": 102,
            "diff": 0
        },
        "numTrans": 4,
        "tradedShares": 50792,
        "amount": 5180784,
        "indicators": {
            "SMA": 104.72999999999999,
            "EMA": 104.16834223774104,
            "RSI": 29.072909333621396,
            "MACD": -1.4601543271656112,
            "MACD_Signal": -1.1008658829779674,
            "MACD_Hist": -0.35928844418764383,
            "BB_High": 109.64491607252859,
            "BB_Low": 99.81508392747139,
            "BB_Mid": 104.72999999999999
        }
    },
    "2024-04-24": {
        "price": {
            "open": 102,
            "max": 102,
            "min": 102,
            "close": 102,
            "prevClose": 102,
            "diff": 0
        },
        "numTrans": 1,
        "tradedShares": 1000,
        "amount": 102000,
        "indicators": {
            "SMA": 104.38,
            "EMA": 103.96183345319427,
            "RSI": 29.07290933362141,
            "MACD": -1.444360229013384,
            "MACD_Signal": -1.1695647521850507,
            "MACD_Hist": -0.27479547682833316,
            "BB_High": 109.01793057300343,
            "BB_Low": 99.74206942699657,
            "BB_Mid": 104.38
        }
    },
    "2024-04-25": {
        "price": {
            "open": 102,
            "max": 102,
            "min": 102,
            "close": 102,
            "prevClose": 102,
            "diff": 0
        },
        "numTrans": 1,
        "tradedShares": 35846,
        "amount": 3656292,
        "indicators": {
            "SMA": 104.08,
            "EMA": 103.77499217193767,
            "RSI": 29.072909333621396,
            "MACD": -1.415525989959491,
            "MACD_Signal": -1.2187569997399388,
            "MACD_Hist": -0.1967689902195522,
            "BB_High": 108.51423048566488,
            "BB_Low": 99.64576951433511,
            "BB_Mid": 104.08
        }
    },
    "2024-05-02": {
        "price": {
            "open": 102,
            "max": 102,
            "min": 102,
            "close": 102,
            "prevClose": 102,
            "diff": 0
        },
        "numTrans": 2,
        "tradedShares": 89415,
        "amount": 9120330,
        "indicators": {
            "SMA": 103.78,
            "EMA": 103.60594529841978,
            "RSI": 29.072909333621396,
            "MACD": -1.3768037116128937,
            "MACD_Signal": -1.25036634211453,
            "MACD_Hist": -0.12643736949836382,
            "BB_High": 107.9145374590152,
            "BB_Low": 99.64546254098481,
            "BB_Mid": 103.78
        }
    },
    "2024-05-05": {
        "price": {
            "open": 100,
            "max": 100,
            "min": 100,
            "close": 100,
            "prevClose": 102,
            "diff": -2
        },
        "numTrans": 1,
        "tradedShares": 51088,
        "amount": 5108800,
        "indicators": {
            "SMA": 103.38,
            "EMA": 103.26252193666551,
            "RSI": 20.89988455781618,
            "MACD": -1.4903198330038663,
            "MACD_Signal": -1.2983570402923972,
            "MACD_Hist": -0.1919627927114691,
            "BB_High": 107.34867736153996,
            "BB_Low": 99.41132263846004,
            "BB_Mid": 103.38
        }
    },
    "2024-05-07": {
        "price": {
            "open": 100,
            "max": 100,
            "min": 100,
            "close": 100,
            "prevClose": 100,
            "diff": 0
        },
        "numTrans": 1,
        "tradedShares": 8500,
        "amount": 850000,
        "indicators": {
            "SMA": 102.97999999999999,
            "EMA": 102.95180556174498,
            "RSI": 20.89988455781618,
            "MACD": -1.5622732633471657,
            "MACD_Signal": -1.351140284903351,
            "MACD_Hist": -0.21113297844381473,
            "BB_High": 106.6030373997517,
            "BB_Low": 99.35696260024828,
            "BB_Mid": 102.97999999999999
        }
    },
    "2024-05-12": {
        "price": {
            "open": 100,
            "max": 100,
            "min": 100,
            "close": 100,
            "prevClose": 100,
            "diff": 0
        },
        "numTrans": 1,
        "tradedShares": 84882,
        "amount": 8488200,
        "indicators": {
            "SMA": 102.68499999999999,
            "EMA": 102.67068122253116,
            "RSI": 20.89988455781618,
            "MACD": -1.600843349646368,
            "MACD_Signal": -1.4010808978519544,
            "MACD_Hist": -0.19976245179441365,
            "BB_High": 106.26956412970942,
            "BB_Low": 99.10043587029055,
            "BB_Mid": 102.68499999999999
        }
    },
    "2024-07-15": {
        "price": {
            "open": 100,
            "max": 100,
            "min": 100,
            "close": 100,
            "prevClose": 100,
            "diff": 0
        },
        "numTrans": 1,
        "tradedShares": 133887,
        "amount": 13388700,
        "indicators": {
            "SMA": 102.39000000000001,
            "EMA": 102.41633062990914,
            "RSI": 20.89988455781618,
            "MACD": -1.6128188491725695,
            "MACD_Signal": -1.4434284881160775,
            "MACD_Hist": -0.16939036105649197,
            "BB_High": 105.83609924407287,
            "BB_Low": 98.94390075592716,
            "BB_Mid": 102.39000000000001
        }
    },
    "2024-08-21": {
        "price": {
            "open": 100,
            "max": 100,
            "min": 100,
            "close": 100,
            "prevClose": 100,
            "diff": 0
        },
        "numTrans": 1,
        "tradedShares": 200,
        "amount": 20000,
        "indicators": {
            "SMA": 102.095,
            "EMA": 102.18620390325113,
            "RSI": 20.89988455781618,
            "MACD": -1.6038216610615024,
            "MACD_Signal": -1.4755071227051624,
            "MACD_Hist": -0.12831453835634,
            "BB_High": 105.28966743183065,
            "BB_Low": 98.90033256816935,
            "BB_Mid": 102.095
        }
    }
}